AUTHORS
CHANGES
COPYING
MANIFEST.in
README.md
TODO
setup.py
examples/superheros.py
tentacles/__init__.py
tentacles/database.py
tentacles/fields.py
tentacles/inheritance.py
tentacles/lazy.py
tentacles/queryset.py
tentacles/sqlcodes.py
tentacles/table.py
tentacles/values.py
tentacles.egg-info/PKG-INFO
tentacles.egg-info/SOURCES.txt
tentacles.egg-info/dependency_links.txt
tentacles.egg-info/top_level.txt
tentacles/backends/__init__.py
tentacles/backends/sqlite3/__init__.py
tentacles/backends/sqlite3/database.py
tentacles/backends/sqlite3/fields.py
tentacles/backends/sqlite3/queryset.py
tentacles/backends/sqlite3/table.py
tentacles/parser/__init__.py
tentacles/parser/opcodes.py
tentacles/parser/py2ast.py
test/01_objectdef.py
test/02_values.py
test/03_fields.py
test/04_objects.py
test/10_dburi.py